plonecli/__init__.py
plonecli/cli.py
plonecli/configure_mrbob.py
plonecli/exceptions.py
plonecli/registry.py
plonecli/configure_mrbob/.mrbob.ini
plonecli-2.2.data/scripts/plonecli_autocomplete.sh
plonecli-2.2.dist-info/AUTHORS.rst
plonecli-2.2.dist-info/LICENSE
plonecli-2.2.dist-info/METADATA
plonecli-2.2.dist-info/WHEEL
plonecli-2.2.dist-info/entry_points.txt
plonecli-2.2.dist-info/top_level.txt
plonecli-2.2.dist-info/RECORD
