Metadata-Version: 2.1
Name: plonecli
Version: 2.2
Summary: A Plone CLI for creating Plone packages
Home-page: https://github.com/plone/plonecli
Author: Maik Derstappen
Author-email: md@derico.de
License: BSD License
Keywords: plonecli
Platform: UNKNOWN
Classifier: Development Status :: 5 - Production/Stable
Classifier: Intended Audience :: Developers
Classifier: License :: OSI Approved :: BSD License
Classifier: Natural Language :: English
Classifier: Topic :: Software Development :: Code Generators
Classifier: Topic :: Software Development :: Build Tools
Classifier: Topic :: Software Development :: Quality Assurance
Classifier: Topic :: Utilities
Classifier: Environment :: Console
Classifier: Framework :: Plone
Classifier: Intended Audience :: Developers
Classifier: Programming Language :: Python :: 3
Classifier: Programming Language :: Python :: 3.6
Classifier: Programming Language :: Python :: 3.7
Classifier: Programming Language :: Python :: 3.8
Requires-Python: >=3.6
Requires-Dist: Click (>=7.0)
Requires-Dist: bobtemplates.plone (>=6.0b12)
Requires-Dist: click-aliases
Requires-Dist: mr.bob
Requires-Dist: setuptools
Requires-Dist: tox
Provides-Extra: dev
Requires-Dist: tox ; extra == 'dev'
Requires-Dist: zest.releaser[recommended] ; extra == 'dev'
Provides-Extra: test
Requires-Dist: isort (>=5.0.0) ; extra == 'test'
Requires-Dist: pytest ; extra == 'test'
